{
  "_class": "group",
  "do_objectID": "AFB80DE0-80A7-4982-BABB-6A4F777F8678",
  "exportOptions": {
    "_class": "exportOptions",
    "exportFormats": [
    ],
    "includedLayerIds": [
    ],
    "layerOptions": 0,
    "shouldTrim": false
  },
  "frame": {
    "_class": "rect",
    "constrainProportions": false,
    "height": 42,
    "width": 56,
    "x": 360,
    "y": 354
  },
  "hasClickThrough": false,
  "isFlippedHorizontal": false,
  "isFlippedVertical": false,
  "isLocked": false,
  "isVisible": true,
  "layerListExpandedType": 0,
  "layers": [
    {
      "class": "shapeGroup",
      "id": "8395140A-8EB0-4C01-9407-8FB9378DCB87"
    },
    {
      "class": "shapeGroup",
      "id": "B4307BB6-044A-4410-877F-0CAD6F47CE53"
    }
  ],
  "name": "Count",
  "nameIsFixed": true,
  "resizingConstraint": 63,
  "resizingType": 0,
  "rotation": 0,
  "shouldBreakMaskChain": false,
  "style": {
    "_class": "style",
    "endDecorationType": 0,
    "miterLimit": 10,
    "startDecorationType": 0
  }
}